pr_assistant/__init__.py
pr_assistant/cli.py
pr_assistant/cli_pip.py
pr_assistant/config_loader.py
pr_assistant/algo/__init__.py
pr_assistant/algo/file_filter.py
pr_assistant/algo/git_patch_processing.py
pr_assistant/algo/language_handler.py
pr_assistant/algo/pr_processing.py
pr_assistant/algo/token_handler.py
pr_assistant/algo/types.py
pr_assistant/algo/utils.py
pr_assistant/algo/ai_handlers/base_ai_handler.py
pr_assistant/algo/ai_handlers/langchain_ai_handler.py
pr_assistant/algo/ai_handlers/litellm_ai_handler.py
pr_assistant/algo/ai_handlers/openai_ai_handler.py
pr_assistant/assistant/__init__.py
pr_assistant/assistant/pr_assistant.py
pr_assistant/git_providers/__init__.py
pr_assistant/git_providers/azuredevops_provider.py
pr_assistant/git_providers/bitbucket_provider.py
pr_assistant/git_providers/bitbucket_server_provider.py
pr_assistant/git_providers/codecommit_client.py
pr_assistant/git_providers/codecommit_provider.py
pr_assistant/git_providers/gerrit_provider.py
pr_assistant/git_providers/git_provider.py
pr_assistant/git_providers/github_provider.py
pr_assistant/git_providers/gitlab_provider.py
pr_assistant/git_providers/local_git_provider.py
pr_assistant/git_providers/utils.py
pr_assistant/identity_providers/__init__.py
pr_assistant/identity_providers/default_identity_provider.py
pr_assistant/identity_providers/identity_provider.py
pr_assistant/log/__init__.py
pr_assistant/secret_providers/__init__.py
pr_assistant/secret_providers/google_cloud_storage_secret_provider.py
pr_assistant/secret_providers/secret_provider.py
pr_assistant/servers/__init__.py
pr_assistant/servers/azuredevops_server_webhook.py
pr_assistant/servers/bitbucket_app.py
pr_assistant/servers/bitbucket_server_webhook.py
pr_assistant/servers/gerrit_server.py
pr_assistant/servers/github_action_runner.py
pr_assistant/servers/github_app.py
pr_assistant/servers/github_polling.py
pr_assistant/servers/gitlab_webhook.py
pr_assistant/servers/gunicorn_config.py
pr_assistant/servers/help.py
pr_action-0.2.2.dist-info/LICENSE
pr_action-0.2.2.dist-info/METADATA
pr_action-0.2.2.dist-info/WHEEL
pr_action-0.2.2.dist-info/entry_points.txt
pr_action-0.2.2.dist-info/top_level.txt
pr_action-0.2.2.dist-info/RECORD
